py_tsyganenko-0.1.6.dist-info/METADATA
py_tsyganenko-0.1.6.dist-info/WHEEL
py_tsyganenko-0.1.6.dist-info/COPYING
py_tsyganenko.cp38-win_amd64.pyd
py_tsyganenko.cp38-win_amd64.dll.a
py_tsyganenko-0.1.6.dist-info/RECORD
