Metadata-Version: 2.1
Name: py-tsyganenko
Version: 0.1.6
Summary: A simple python wrapper of N. A. Tsyganenko Fortran models and Geopack module
Home-page: https://github.com/LaboratoryOfPlasmaPhysics/py_tsyganenko
Author-Email: Alexis Jeandet <alexis.jeandet@member.fsf.org>
License:                     GNU GENERAL PUBLIC LICENSE
Classifier: Development Status :: 2 - Pre-Alpha
Classifier: Intended Audience :: Developers
Classifier: License :: OSI Approved :: GNU General Public License v3 (GPLv3)
Classifier: Natural Language :: English
Classifier: Programming Language :: Python :: 3
Classifier: Programming Language :: Python :: 3.7
Classifier: Programming Language :: Python :: 3.8
Classifier: Programming Language :: Python :: 3.9
Classifier: Programming Language :: Python :: 3.10
Classifier: Programming Language :: Python :: 3.11
Project-URL: Homepage, https://github.com/LaboratoryOfPlasmaPhysics/py_tsyganenko
Requires-Python: >=3.7
Requires-Dist: numpy
